setup.py
evepi/__init__.py
evepi/acc_01.py
evepi/air_01.py
evepi/inf_01.py
evepi/inp_01.py
evepi/out_01.py
evepi/snd_01.py
evepi/tem_01.py
evepi/tus_01.py
evepi/ultrason.py
evepi.egg-info/PKG-INFO
evepi.egg-info/SOURCES.txt
evepi.egg-info/dependency_links.txt
evepi.egg-info/top_level.txt