Metadata-Version: 1.0
Name: evepi
Version: 0.70
Summary: evepi
Home-page: http://evepi.cc
Author: Zhang Yiwei
Author-email: Karl1991223@126.com
License: public domain
Keywords: evepi,adamsolo,arduino
Platform: any
